openai_websearch_mcp/__init__.py
openai_websearch_mcp/__main__.py
openai_websearch_mcp/cli.py
openai_websearch_mcp/server.py
iflow_mcp_openai_websearch_mcp-0.4.3.dist-info/METADATA
iflow_mcp_openai_websearch_mcp-0.4.3.dist-info/WHEEL
iflow_mcp_openai_websearch_mcp-0.4.3.dist-info/entry_points.txt
iflow_mcp_openai_websearch_mcp-0.4.3.dist-info/licenses/LICENSE
iflow_mcp_openai_websearch_mcp-0.4.3.dist-info/RECORD
